driva_rfb/__init__.py
driva_rfb/__main__.py
driva_rfb/download.py
driva_rfb/main.py
driva_rfb/scripts/combine.sh
driva_rfb-1.2.0.dist-info/entry_points.txt
driva_rfb-1.2.0.dist-info/WHEEL
driva_rfb-1.2.0.dist-info/METADATA
driva_rfb-1.2.0.dist-info/RECORD
