Metadata-Version: 2.1
Name: driva-rfb
Version: 1.2.0
Summary: 
Author: Victor Belinello
Author-email: victor@datadriva.com
Requires-Python: >=3.9,<4.0
Classifier: Programming Language :: Python :: 3
Classifier: Programming Language :: Python :: 3.10
Classifier: Programming Language :: Python :: 3.9
Requires-Dist: beautifulsoup4 (>=4.10.0,<5.0.0)
Requires-Dist: httpx (>=0.22.0,<0.23.0)
Requires-Dist: pandas (>=1.4.1,<2.0.0)
Requires-Dist: pywget (>=0.31,<0.32)
Requires-Dist: requests (>=2.27.1,<3.0.0)
Requires-Dist: typer[all] (>=0.4.0,<0.5.0)
